LICENCE.txt
README.md
setup.cfg
setup.py
rey/__init__.py
rey/http.py
rey_wrapper.egg-info/PKG-INFO
rey_wrapper.egg-info/SOURCES.txt
rey_wrapper.egg-info/dependency_links.txt
rey_wrapper.egg-info/requires.txt
rey_wrapper.egg-info/top_level.txt