Metadata-Version: 2.1
Name: rey-wrapper
Version: 0.1
Summary: An API wrapper designed to simplify the process of integrating Line Messaging API
Home-page: https://github.com/TheGenocides/rey
Download-URL: https://github.com/TheGenocides/rey/archive/refs/tags/v0.1.tar.gz
Author: TheGenocide
Author-email: luke.genesis.hyder@gmail.com
License: MIT
Keywords: line-bot,apiwrapper,line,api
Classifier: Development Status :: 4 - Beta
Classifier: Intended Audience :: Developers
Classifier: Topic :: Software Development :: Build Tools
Classifier: License :: OSI Approved :: MIT License
Classifier: Programming Language :: Python :: 3.7
Classifier: Programming Language :: Python :: 3.10
Classifier: Programming Language :: Python :: 3.11
License-File: LICENCE.txt
